pyslack/__init__.py
pyslack/plot.py
pyslackline/__init__.py
pyslackline/plot.py
pyslackline-0.0.1.dist-info/LICENSE
pyslackline-0.0.1.dist-info/METADATA
pyslackline-0.0.1.dist-info/WHEEL
pyslackline-0.0.1.dist-info/top_level.txt
pyslackline-0.0.1.dist-info/RECORD
